logging2/__init__.py
logging2/config.py
logging2/handlers.py
logging_command-0.1.dist-info/METADATA
logging_command-0.1.dist-info/WHEEL
logging_command-0.1.dist-info/top_level.txt
logging_command-0.1.dist-info/RECORD
