Metadata-Version: 2.1
Name: logging-command
Version: 0.1
Summary: clinical trial information retriver
Home-page: https://github.com/PQR96137/logging2
Author: PQR96137
Author-email: jay3864660@gmail.com
License: MIT
Platform: UNKNOWN
